{
  "date": "2026-07-07",
  "time": "09:26:58",
  "timezone": "America/New_York",
  "mode": "premarket",
  "regime": "NEUTRAL",
  "universe_size": 194,
  "screened_count": 36,
  "picks": [
    {
      "symbol": "AAPL",
      "score": 25.5,
      "price": 313.81,
      "entry_low": 302.46,
      "entry_high": 322.04,
      "gap_pct": 1.31,
      "volume_premarket": 49130304,
      "market_cap": 0,
      "sector": "Unknown",
      "source": "premarket",
      "pm_metrics": {
        "close_prev": 308.63,
        "open_today": 312.66,
        "high_pm": 314.2,
        "low_pm": 307.01
      },
      "change_pct": 0.37,
      "volume": 13347999,
      "vwap": 312.6,
      "above_vwap": true
    },
    {
      "symbol": "ABBV",
      "score": 25.0,
      "price": 257.79,
      "entry_low": 255.85,
      "entry_high": 262.4,
      "gap_pct": -2.42,
      "volume_premarket": 6874406,
      "market_cap": 0,
      "sector": "Unknown",
      "source": "premarket",
      "pm_metrics": {
        "close_prev": 261.07,
        "open_today": 254.76,
        "high_pm": 260.92,
        "low_pm": 253.61
      },
      "change_pct": 1.19,
      "volume": 1318637,
      "vwap": 258.29,
      "above_vwap": false
    },
    {
      "symbol": "ABT",
      "score": 27.7,
      "price": 96.66,
      "entry_low": 93.49,
      "entry_high": 98.5,
      "gap_pct": 0.24,
      "volume_premarket": 14408435,
      "market_cap": 0,
      "sector": "Unknown",
      "source": "premarket",
      "pm_metrics": {
        "close_prev": 95.4,
        "open_today": 95.63,
        "high_pm": 95.91,
        "low_pm": 92.99
      },
      "change_pct": 1.07,
      "volume": 2850176,
      "vwap": 97.58,
      "above_vwap": false
    },
    {
      "symbol": "ACN",
      "score": 25.0,
      "price": 142.7,
      "entry_low": 134.6,
      "entry_high": 141.07,
      "gap_pct": -0.28,
      "volume_premarket": 6820905,
      "market_cap": 0,
      "sector": "Unknown",
      "source": "premarket",
      "pm_metrics": {
        "close_prev": 137.35,
        "open_today": 136.96,
        "high_pm": 138.11,
        "low_pm": 133.5
      },
      "change_pct": 4.19,
      "volume": 2281566,
      "vwap": 141.89,
      "above_vwap": true
    },
    {
      "symbol": "ADBE",
      "score": 25.0,
      "price": 227.34,
      "entry_low": 215.33,
      "entry_high": 224.61,
      "gap_pct": -0.75,
      "volume_premarket": 4316764,
      "market_cap": 0,
      "sector": "Unknown",
      "source": "premarket",
      "pm_metrics": {
        "close_prev": 219.72,
        "open_today": 218.07,
        "high_pm": 219.76,
        "low_pm": 212.9
      },
      "change_pct": 4.25,
      "volume": 2750713,
      "vwap": 223.22,
      "above_vwap": true
    },
    {
      "symbol": "AEE",
      "score": 25.0,
      "price": 115.56,
      "entry_low": 112.72,
      "entry_high": 116.38,
      "gap_pct": -1.76,
      "volume_premarket": 864465,
      "market_cap": 0,
      "sector": "Unknown",
      "source": "premarket",
      "pm_metrics": {
        "close_prev": 115.02,
        "open_today": 112.99,
        "high_pm": 114.78,
        "low_pm": 112.91
      },
      "change_pct": 2.27,
      "volume": 199528,
      "vwap": 115.59,
      "above_vwap": false
    },
    {
      "symbol": "AEP",
      "score": 25.0,
      "price": 139.63,
      "entry_low": 135.74,
      "entry_high": 140.06,
      "gap_pct": -1.83,
      "volume_premarket": 7193170,
      "market_cap": 0,
      "sector": "Unknown",
      "source": "premarket",
      "pm_metrics": {
        "close_prev": 138.51,
        "open_today": 135.98,
        "high_pm": 138.46,
        "low_pm": 135.23
      },
      "change_pct": 2.69,
      "volume": 869094,
      "vwap": 139.35,
      "above_vwap": true
    },
    {
      "symbol": "AES",
      "score": 33.7,
      "price": 14.62,
      "entry_low": 14.29,
      "entry_high": 15.01,
      "gap_pct": -0.07,
      "volume_premarket": 6873863,
      "market_cap": 0,
      "sector": "Unknown",
      "source": "premarket",
      "pm_metrics": {
        "close_prev": 14.58,
        "open_today": 14.57,
        "high_pm": 14.64,
        "low_pm": 14.53
      },
      "change_pct": 0.34,
      "volume": 2018708,
      "vwap": 14.61,
      "above_vwap": true
    },
    {
      "symbol": "ALLY",
      "score": 30.1,
      "price": 45.77,
      "entry_low": 45.31,
      "entry_high": 49.26,
      "gap_pct": 3.46,
      "volume_premarket": 0,
      "market_cap": 0,
      "sector": "Unknown",
      "source": "premarket",
      "pm_metrics": {
        "close_prev": 46.23,
        "open_today": 47.83,
        "high_pm": 47.83,
        "low_pm": 45.54
      },
      "change_pct": -1.01,
      "volume": 204131,
      "vwap": 46.03,
      "above_vwap": false
    },
    {
      "symbol": "CG",
      "score": 32.0,
      "price": 43.86,
      "entry_low": 43.15,
      "entry_high": 49.14,
      "gap_pct": 8.36,
      "volume_premarket": 0,
      "market_cap": 0,
      "sector": "Unknown",
      "source": "premarket",
      "pm_metrics": {
        "close_prev": 44.03,
        "open_today": 47.71,
        "high_pm": 47.71,
        "low_pm": 43.1
      },
      "change_pct": -0.41,
      "volume": 399770,
      "vwap": 44.04,
      "above_vwap": false
    },
    {
      "symbol": "CNP",
      "score": 32.4,
      "price": 44.79,
      "entry_low": 43.14,
      "entry_high": 49.42,
      "gap_pct": 9.0,
      "volume_premarket": 0,
      "market_cap": 0,
      "sector": "Unknown",
      "source": "premarket",
      "pm_metrics": {
        "close_prev": 44.02,
        "open_today": 47.98,
        "high_pm": 47.98,
        "low_pm": 43.65
      },
      "change_pct": 1.8,
      "volume": 798995,
      "vwap": 44.78,
      "above_vwap": true
    },
    {
      "symbol": "CNX",
      "score": 29.8,
      "price": 33.48,
      "entry_low": 32.71,
      "entry_high": 39.98,
      "gap_pct": 16.31,
      "volume_premarket": 0,
      "market_cap": 0,
      "sector": "Unknown",
      "source": "premarket",
      "pm_metrics": {
        "close_prev": 33.38,
        "open_today": 38.82,
        "high_pm": 38.82,
        "low_pm": 33.16
      },
      "change_pct": 0.3,
      "volume": 389569,
      "vwap": 33.31,
      "above_vwap": true
    },
    {
      "symbol": "CSX",
      "score": 31.4,
      "price": 48.7,
      "entry_low": 47.86,
      "entry_high": 53.45,
      "gap_pct": 6.24,
      "volume_premarket": 0,
      "market_cap": 0,
      "sector": "Unknown",
      "source": "premarket",
      "pm_metrics": {
        "close_prev": 48.84,
        "open_today": 51.89,
        "high_pm": 51.89,
        "low_pm": 48.71
      },
      "change_pct": -0.24,
      "volume": 2411170,
      "vwap": 48.84,
      "above_vwap": false
    },
    {
      "symbol": "DVN",
      "score": 28.3,
      "price": 41.29,
      "entry_low": 39.55,
      "entry_high": 44.21,
      "gap_pct": 6.34,
      "volume_premarket": 0,
      "market_cap": 0,
      "sector": "Unknown",
      "source": "premarket",
      "pm_metrics": {
        "close_prev": 40.36,
        "open_today": 42.92,
        "high_pm": 42.92,
        "low_pm": 40.05
      },
      "change_pct": 2.3,
      "volume": 2822700,
      "vwap": 41.18,
      "above_vwap": true
    },
    {
      "symbol": "EQT",
      "score": 29.5,
      "price": 51.88,
      "entry_low": 50.68,
      "entry_high": 56.67,
      "gap_pct": 6.39,
      "volume_premarket": 0,
      "market_cap": 0,
      "sector": "Unknown",
      "source": "premarket",
      "pm_metrics": {
        "close_prev": 51.72,
        "open_today": 55.02,
        "high_pm": 55.02,
        "low_pm": 51.67
      },
      "change_pct": 0.33,
      "volume": 1198035,
      "vwap": 51.71,
      "above_vwap": true
    },
    {
      "symbol": "EXC",
      "score": 32.6,
      "price": 48.27,
      "entry_low": 46.11,
      "entry_high": 51.68,
      "gap_pct": 6.63,
      "volume_premarket": 0,
      "market_cap": 0,
      "sector": "Unknown",
      "source": "premarket",
      "pm_metrics": {
        "close_prev": 47.05,
        "open_today": 50.17,
        "high_pm": 50.17,
        "low_pm": 46.95
      },
      "change_pct": 2.59,
      "volume": 2373821,
      "vwap": 48.13,
      "above_vwap": true
    },
    {
      "symbol": "FE",
      "score": 32.2,
      "price": 48.86,
      "entry_low": 46.76,
      "entry_high": 52.56,
      "gap_pct": 6.96,
      "volume_premarket": 0,
      "market_cap": 0,
      "sector": "Unknown",
      "source": "premarket",
      "pm_metrics": {
        "close_prev": 47.71,
        "open_today": 51.03,
        "high_pm": 51.03,
        "low_pm": 47.64
      },
      "change_pct": 2.41,
      "volume": 559549,
      "vwap": 48.72,
      "above_vwap": true
    },
    {
      "symbol": "IRDM",
      "score": 28.9,
      "price": 51.45,
      "entry_low": 51.52,
      "entry_high": 57.05,
      "gap_pct": 5.36,
      "volume_premarket": 0,
      "market_cap": 0,
      "sector": "Unknown",
      "source": "premarket",
      "pm_metrics": {
        "close_prev": 52.57,
        "open_today": 55.39,
        "high_pm": 55.39,
        "low_pm": 52.22
      },
      "change_pct": -2.17,
      "volume": 944673,
      "vwap": 51.73,
      "above_vwap": false
    },
    {
      "symbol": "LYB",
      "score": 28.8,
      "price": 53.97,
      "entry_low": 51.85,
      "entry_high": 57.84,
      "gap_pct": 6.14,
      "volume_premarket": 0,
      "market_cap": 0,
      "sector": "Unknown",
      "source": "premarket",
      "pm_metrics": {
        "close_prev": 52.91,
        "open_today": 56.16,
        "high_pm": 56.16,
        "low_pm": 52.21
      },
      "change_pct": 1.9,
      "volume": 1108157,
      "vwap": 54.23,
      "above_vwap": false
    },
    {
      "symbol": "MAA",
      "score": 25.0,
      "price": 144.15,
      "entry_low": 139.35,
      "entry_high": 144.99,
      "gap_pct": -1.0,
      "volume_premarket": 420354,
      "market_cap": 0,
      "sector": "Unknown",
      "source": "premarket",
      "pm_metrics": {
        "close_prev": 142.19,
        "open_today": 140.77,
        "high_pm": 142.23,
        "low_pm": 140.62
      },
      "change_pct": 2.4,
      "volume": 86961,
      "vwap": 143.37,
      "above_vwap": true
    },
    {
      "symbol": "MC",
      "score": 43.8,
      "price": 71.25,
      "entry_low": 67.18,
      "entry_high": 74.1,
      "gap_pct": 4.95,
      "volume_premarket": 507151,
      "market_cap": 0,
      "sector": "Unknown",
      "source": "premarket",
      "pm_metrics": {
        "close_prev": 68.55,
        "open_today": 71.94,
        "high_pm": 72.39,
        "low_pm": 69.08
      },
      "change_pct": -0.97,
      "volume": 83751,
      "vwap": 71.56,
      "above_vwap": false
    },
    {
      "symbol": "MCD",
      "score": 25.0,
      "price": 284.03,
      "entry_low": 275.02,
      "entry_high": 287.88,
      "gap_pct": -0.4,
      "volume_premarket": 6722647,
      "market_cap": 0,
      "sector": "Unknown",
      "source": "premarket",
      "pm_metrics": {
        "close_prev": 280.63,
        "open_today": 279.5,
        "high_pm": 281.02,
        "low_pm": 273.58
      },
      "change_pct": 1.62,
      "volume": 1296676,
      "vwap": 285.16,
      "above_vwap": false
    },
    {
      "symbol": "MDT",
      "score": 35.2,
      "price": 84.54,
      "entry_low": 81.53,
      "entry_high": 85.55,
      "gap_pct": -0.16,
      "volume_premarket": 10558408,
      "market_cap": 0,
      "sector": "Unknown",
      "source": "premarket",
      "pm_metrics": {
        "close_prev": 83.19,
        "open_today": 83.06,
        "high_pm": 83.77,
        "low_pm": 81.41
      },
      "change_pct": 1.78,
      "volume": 2883997,
      "vwap": 85.4,
      "above_vwap": false
    },
    {
      "symbol": "META",
      "score": 26.2,
      "price": 606.15,
      "entry_low": 571.24,
      "entry_high": 618.3,
      "gap_pct": 2.98,
      "volume_premarket": 15914218,
      "market_cap": 0,
      "sector": "Unknown",
      "source": "premarket",
      "pm_metrics": {
        "close_prev": 582.9,
        "open_today": 600.29,
        "high_pm": 603.58,
        "low_pm": 581.76
      },
      "change_pct": 0.98,
      "volume": 6274490,
      "vwap": 609.76,
      "above_vwap": false
    },
    {
      "symbol": "MOS",
      "score": 37.8,
      "price": 20.94,
      "entry_low": 20.71,
      "entry_high": 21.82,
      "gap_pct": 0.24,
      "volume_premarket": 7620816,
      "market_cap": 0,
      "sector": "Unknown",
      "source": "premarket",
      "pm_metrics": {
        "close_prev": 21.13,
        "open_today": 21.18,
        "high_pm": 21.43,
        "low_pm": 20.82
      },
      "change_pct": -1.13,
      "volume": 2439034,
      "vwap": 20.91,
      "above_vwap": true
    },
    {
      "symbol": "MPC",
      "score": 25.4,
      "price": 266.51,
      "entry_low": 261.02,
      "entry_high": 277.06,
      "gap_pct": 0.99,
      "volume_premarket": 1361346,
      "market_cap": 0,
      "sector": "Unknown",
      "source": "premarket",
      "pm_metrics": {
        "close_prev": 266.35,
        "open_today": 268.99,
        "high_pm": 272.35,
        "low_pm": 265.45
      },
      "change_pct": -0.92,
      "volume": 446758,
      "vwap": 266.98,
      "above_vwap": false
    },
    {
      "symbol": "MRK",
      "score": 25.0,
      "price": 129.12,
      "entry_low": 126.97,
      "entry_high": 130.58,
      "gap_pct": -2.15,
      "volume_premarket": 9219156,
      "market_cap": 0,
      "sector": "Unknown",
      "source": "premarket",
      "pm_metrics": {
        "close_prev": 129.56,
        "open_today": 126.78,
        "high_pm": 130.0,
        "low_pm": 125.62
      },
      "change_pct": 1.85,
      "volume": 1729412,
      "vwap": 128.9,
      "above_vwap": true
    },
    {
      "symbol": "MUR",
      "score": 28.5,
      "price": 32.47,
      "entry_low": 31.08,
      "entry_high": 37.92,
      "gap_pct": 16.11,
      "volume_premarket": 0,
      "market_cap": 0,
      "sector": "Unknown",
      "source": "premarket",
      "pm_metrics": {
        "close_prev": 31.71,
        "open_today": 36.82,
        "high_pm": 36.82,
        "low_pm": 31.5
      },
      "change_pct": 2.36,
      "volume": 195833,
      "vwap": 32.35,
      "above_vwap": true
    },
    {
      "symbol": "NI",
      "score": 32.7,
      "price": 47.68,
      "entry_low": 46.11,
      "entry_high": 52.19,
      "gap_pct": 7.68,
      "volume_premarket": 0,
      "market_cap": 0,
      "sector": "Unknown",
      "source": "premarket",
      "pm_metrics": {
        "close_prev": 47.05,
        "open_today": 50.67,
        "high_pm": 50.67,
        "low_pm": 47.02
      },
      "change_pct": 1.34,
      "volume": 628920,
      "vwap": 47.77,
      "above_vwap": false
    },
    {
      "symbol": "NKE",
      "score": 30.0,
      "price": 43.25,
      "entry_low": 42.47,
      "entry_high": 47.33,
      "gap_pct": 6.02,
      "volume_premarket": 0,
      "market_cap": 0,
      "sector": "Unknown",
      "source": "premarket",
      "pm_metrics": {
        "close_prev": 43.34,
        "open_today": 45.95,
        "high_pm": 45.95,
        "low_pm": 41.84
      },
      "change_pct": -0.21,
      "volume": 4930030,
      "vwap": 43.58,
      "above_vwap": false
    },
    {
      "symbol": "OXY",
      "score": 31.4,
      "price": 50.25,
      "entry_low": 47.83,
      "entry_high": 53.54,
      "gap_pct": 6.49,
      "volume_premarket": 0,
      "market_cap": 0,
      "sector": "Unknown",
      "source": "premarket",
      "pm_metrics": {
        "close_prev": 48.81,
        "open_today": 51.98,
        "high_pm": 51.98,
        "low_pm": 48.7
      },
      "change_pct": 2.95,
      "volume": 2444847,
      "vwap": 50.13,
      "above_vwap": true
    },
    {
      "symbol": "PYPL",
      "score": 31.0,
      "price": 45.52,
      "entry_low": 44.21,
      "entry_high": 49.19,
      "gap_pct": 5.87,
      "volume_premarket": 0,
      "market_cap": 0,
      "sector": "Unknown",
      "source": "premarket",
      "pm_metrics": {
        "close_prev": 45.11,
        "open_today": 47.76,
        "high_pm": 47.76,
        "low_pm": 43.81
      },
      "change_pct": 0.96,
      "volume": 4023188,
      "vwap": 45.65,
      "above_vwap": false
    },
    {
      "symbol": "RRC",
      "score": 26.7,
      "price": 37.94,
      "entry_low": 36.54,
      "entry_high": 41.05,
      "gap_pct": 6.87,
      "volume_premarket": 0,
      "market_cap": 0,
      "sector": "Unknown",
      "source": "premarket",
      "pm_metrics": {
        "close_prev": 37.29,
        "open_today": 39.85,
        "high_pm": 39.85,
        "low_pm": 37.28
      },
      "change_pct": 1.7,
      "volume": 430325,
      "vwap": 37.82,
      "above_vwap": true
    },
    {
      "symbol": "TPG",
      "score": 29.5,
      "price": 42.27,
      "entry_low": 41.75,
      "entry_high": 46.5,
      "gap_pct": 5.99,
      "volume_premarket": 0,
      "market_cap": 0,
      "sector": "Unknown",
      "source": "premarket",
      "pm_metrics": {
        "close_prev": 42.6,
        "open_today": 45.15,
        "high_pm": 45.15,
        "low_pm": 41.36
      },
      "change_pct": -0.75,
      "volume": 245237,
      "vwap": 42.5,
      "above_vwap": false
    },
    {
      "symbol": "UDR",
      "score": 30.4,
      "price": 41.94,
      "entry_low": 40.14,
      "entry_high": 45.97,
      "gap_pct": 8.96,
      "volume_premarket": 0,
      "market_cap": 0,
      "sector": "Unknown",
      "source": "premarket",
      "pm_metrics": {
        "close_prev": 40.96,
        "open_today": 44.63,
        "high_pm": 44.63,
        "low_pm": 40.67
      },
      "change_pct": 2.39,
      "volume": 308166,
      "vwap": 41.74,
      "above_vwap": true
    },
    {
      "symbol": "VZ",
      "score": 29.1,
      "price": 43.09,
      "entry_low": 41.25,
      "entry_high": 45.92,
      "gap_pct": 5.92,
      "volume_premarket": 0,
      "market_cap": 0,
      "sector": "Unknown",
      "source": "premarket",
      "pm_metrics": {
        "close_prev": 42.09,
        "open_today": 44.58,
        "high_pm": 44.58,
        "low_pm": 41.64
      },
      "change_pct": 2.41,
      "volume": 13809914,
      "vwap": 43.22,
      "above_vwap": false
    },
    {
      "symbol": "NET",
      "score": 48.3,
      "price": 261.27,
      "entry_low": 259.96,
      "entry_high": 262.58,
      "change_pct": 5.54,
      "volume": 1639892,
      "avg_volume": 3271857,
      "rel_volume": 0.5,
      "vwap": 258.63,
      "above_vwap": true,
      "source": "midscreen",
      "time": "11:36:12"
    }
  ],
  "last_midscreen": "11:36:22",
  "midscreen_count": 1,
  "validation": {
    "valid_count": 36,
    "removed_count": 0,
    "removed_symbols": [],
    "new_count": 1
  }
}