{
  "date": "2026-07-07",
  "time": "09:29:47",
  "positions": {
    "AAPL": {
      "symbol": "AAPL",
      "qty": 130,
      "avg_entry_price": 309.055385,
      "market_value": 40953.9,
      "unrealized_pl": 776.69995,
      "unrealized_plpc": 0.01933,
      "current_price": 315.03
    },
    "ABBV": {
      "symbol": "ABBV",
      "qty": 92,
      "avg_entry_price": 257.738478,
      "market_value": 23783.84,
      "unrealized_pl": 71.900024,
      "unrealized_plpc": 0.00303,
      "current_price": 258.52
    },
    "ABT": {
      "symbol": "ABT",
      "qty": 262,
      "avg_entry_price": 93.600344,
      "market_value": 25437.58,
      "unrealized_pl": 914.289872,
      "unrealized_plpc": 0.03728,
      "current_price": 97.09
    }
  }
}